data/build/adjective
data/build/city
data/build/female-name
data/build/first-name
data/build/last-name
data/build/male-name
data/build/noun
data/build/verb
flexihumanhash/__init__.py
flexihumanhash/dict.py
flexihumanhash/filter.py
flexihumanhash/hash.py
flexihumanhash/rand.py
flexihumanhash-0.9.3.dist-info/METADATA
flexihumanhash-0.9.3.dist-info/WHEEL
flexihumanhash-0.9.3.dist-info/RECORD
