Metadata-Version: 2.1
Name: flexihumanhash
Version: 0.9.3
Summary: Makes hashes readable by humans and gives the developer control over how the output looks.
Home-page: https://github.com/apowers313/pyFlexiHumanHash
License: MIT
Keywords: hash,human,cryptography,template,md5,sha256
Author: Adam Powers
Author-email: apowers@ato.ms
Requires-Python: >=3.10,<4.0
Classifier: Intended Audience :: Developers
Classifier: License :: OSI Approved :: MIT License
Classifier: Programming Language :: Python :: 3
Classifier: Programming Language :: Python :: 3.10
Classifier: Programming Language :: Python :: 3.11
Classifier: Topic :: Scientific/Engineering
Classifier: Topic :: Security :: Cryptography
Classifier: Topic :: Software Development :: Libraries :: Python Modules
Classifier: Topic :: System :: Archiving
Classifier: Topic :: Utilities
Requires-Dist: jinja2 (>=3.1.4,<4.0.0)
Project-URL: Repository, https://github.com/apowers313/pyFlexiHumanHash
